{
  "url": "https://www.seriouseats.com/bacon-wrapped-chicken-skewers-pineapple-teriyaki-recipe",
  "image_url": "https://www.seriouseats.com/thmb/ZMs9vReC7shO-_FEnLTUw1mDEy0=/1500x0/filters:no_upscale():max_bytes(150000):strip_icc()/__opt__aboutcom__coeus__resources__content_migration__serious_eats__seriouseats.com__recipes__images__2013__06__20130621-256763-bacon-wrapped-chicken-skewers-9f3b4601e1354f6b84a2af56d7829455.jpg",
  "tags": [
    "Grilled Chicken",
    "Dairy-free Mains",
    "Chicken Breast",
    "Pineapple",
    "Bacon"
  ],
  "title": "Bacon-Wrapped Chicken Skewers With Pineapple and Teriyaki Sauce Recipe",
  "full_text": "Bacon-Wrapped Chicken Skewers With Pineapple and Teriyaki Sauce Recipe\nClose\nJump to recipe\nPrep\n10 mins\nCook\n10 mins\nActive\n30 mins\nBrining and Resting Time\n50 mins\nTotal\n70 mins\nServes\n6\nto 8 servings\nCook Mode\n(Keep screen awake)\nIngredients\nFor the Brine:\n7\ncups\ncold\nwater\n1 1/2\ncups\nsoy sauce\n1/4\ncup\ngranulated sugar\n2\ntablespoons\nkosher salt\nFor the Chicken:\n2\npounds\nboneless skinless chicken breasts\n1\npound\nhalved bacon slices\n1\nlarge\npineapple\n, peeled, cored, and cut into 1-inch cubes\nTo Cook:\n1\ncup\nteriyaki sauce\nDirections\nTo make the brine:\nWhisk together water, soy sauce, sugar, and salt in a large bowl until solids are completely dissolved. Place chicken breast in brine and refrigerate for 45 minutes. Remove chicken from brine and pat dry with paper towels.\nFor the Chicken:\nCut chicken into 1-inch cubes. Wrap each piece of chicken with 1/2 a slice of bacon. Thread bacon-wrapped chicken on skewers, alternating with pineapple cubes.\nLight one chimney full of charcoal.\nWhen all charcoal is lit and covered with gray ash, pour out and spread the coals evenly over entire surface of coal grate. Set cooking grate in place, cover grill and allow to preheat for 5 minutes.\nClean\nand\noil\nthe grilling grate. Grill skewers until bacon has browned and crisped and chicken has cooked through, 3-4 minutes per side. In the last minute of cooking, brush each skewer with teriyaki sauce all over. Remove to a platter, let rest for 5 minutes, then serve immediately with remaining teriyaki sauce.\nSpecial equipment\nGrill, bamboo skewers (pre-soaked in water for at least 30 minutes prior)\nThis Recipe Appears In\nGrilling: Bacon-Wrapped Chicken Skewers with Pineapple and Teriyaki Sauce\nHow to Make Great Grilled Kebabs\nGrilled Chicken\nDairy-free Mains\nChicken Breast\nPineapple\nBacon"
}