{
  "url": "https://www.seriouseats.com/collard-greens-braised-in-coconut-milk-and-tomato-recipe",
  "image_url": "https://www.seriouseats.com/thmb/4rla_kFJvJU27d4lMcflJAJDW0E=/1500x0/filters:no_upscale():max_bytes(150000):strip_icc()/__opt__aboutcom__coeus__resources__content_migration__serious_eats__seriouseats.com__recipes__images__20100729-cardamom-primary-485d021ccd22487eabe72caea48c7639.jpg",
  "tags": [
    "Vegetable Sides",
    "Braised & Stewed Vegetables",
    "Collard Greens"
  ],
  "title": "Collard Greens Braised in Coconut Milk and Tomato Recipe",
  "full_text": "Collard Greens Braised in Coconut Milk and Tomato Recipe\nClose\nJump to recipe\nCook\n70 mins\nTotal\n70 mins\nServes\n6 servings\nCook Mode\n(Keep screen awake)\nIngredients\n2\nlarge bunches\nof\ncollard greens\n, cut into inch-thick ribbons\n2\nlarge\nyellow onions\n, sliced into thin half-moons\n4\nplum\ntomatoes\n, diced (about\n1\n(15 oz.) can\nof diced tomatoes)\n1\n(13.5 oz.) can\nof\ncoconut milk\n1\nteaspoon\nof\ncumin seeds\n1\npinch\nasafoetida\n3\nblack\ncardamom pods\n1\ntablespoon\ncoriander seeds\n, toasted and ground\n1\nteaspoon\nground medium-hot chile, or half-sharp\npaprika\nJuice\nof half a\nlime\n1/3\ncup\noil\nDirections\nIn a large Dutch oven, heat the oil on medium-high. Toss in a cumin seed. When it cracks and sizzles, add in the rest of the cumin, asafoetida, and black cardamom. Stir 30 seconds, then add the remaining spices. Let them cook for another 30 seconds.\nAdd the onions and a pinch of salt. Cook the onions on medium, stirring every now and then, till they\u2019ve softened significantly and have started to brown. Add the tomatoes with another small pinch of salt and cook till softened.\nAdd collards by the handful, coating them in oil as you go, till all are incorporated. Add another small pinch of salt, the coconut milk, and 1/4 cup of water. Stir to combine, then cover and cook for about 40 minutes, or until the greens are tender.\nLift the lid and check for seasoning. You can reduce the sauce if you like, but this is intended to be served over rice, so it should be a little loose. Just before serving, stir in the lime juice.\nThis Recipe Appears In\nSpice Hunting: Black Cardamom\nVegetable Sides\nBraised & Stewed Vegetables\nCollard Greens"
}