{
  "url": "https://www.seriouseats.com/daiquiri-recipe",
  "image_url": "https://www.seriouseats.com/thmb/12TwBogo0W2yT_DaDHeq872_HFw=/1500x0/filters:no_upscale():max_bytes(150000):strip_icc()/20230530-SEA-Daquiri-TwoBites-hero-97ed52eaf96f443a99948f9b0088c371.jpg",
  "tags": [
    "Rum",
    "Summer"
  ],
  "title": "Daiquiri Recipe",
  "full_text": "Daiquiri Recipe\nClose\nJump to recipe\nPrep\n5 mins\nTotal\n5 mins\nServes\n1 serving\nCook Mode\n(Keep screen awake)\nIngredients\n2\nounces\nlight rum\n(you can also use gold rum, but dark rum can be too heavy)\n3/4\nounce\nfresh-squeezed lime juice\n(about\n1/2\nof a\nlime\n)\n1\nteaspoon\nsugar\nDirections\nPour sugar and lime juice into a cocktail shaker and stir until sugar is dissolved. Add the rum and fill shaker with ice; shake well for 10 seconds and strain into a chilled cocktail glass. Garnish with a wedge of lime.\nSerious Eats / Two Bites\nSpecial equipment\nCocktail shaker, cocktail strainer\nThis Recipe Appears In\nSummer of Rum--Or is that Rhum?\nRum\nSummer"
}