{
  "url": "https://www.seriouseats.com/easy-black-forest-chocolate-cake-recipe",
  "image_url": "https://www.seriouseats.com/thmb/my787DesB_cziDfj-_OczZUnlAQ=/1500x0/filters:no_upscale():max_bytes(150000):strip_icc()/__opt__aboutcom__coeus__resources__content_migration__serious_eats__seriouseats.com__recipes__images__2012__06__20120612-127677-LTE-Black-Forest-PRIMARY-ec45ae56afab43ca982d812d9a881f57.jpg",
  "tags": [
    "Cakes",
    "German",
    "Baking",
    "Chocolate"
  ],
  "title": "Easy Black Forest Cake Recipe",
  "full_text": "Easy Black Forest Cake Recipe\nClose\nJump to recipe\nPrep\n10 mins\nCook\n30 mins\nActive\n30 mins\nCooling Time\n60 mins\nTotal\n100 mins\nServes\n12 servings\nCook Mode\n(Keep screen awake)\nIngredients\nFor the Cake:\n3/4\ncup\nkirsch\n1\ncup\npitted\ndried cherries\nBaking spray\n2\ncups\n(about\n14\nounces\n)\ngranulated sugar\n1 3/4\ncups\nall-purpose flour\n(about\n8 3/4\nounces\n)\n1\ncup\nnatural\nunsweetened cocoa powder\n1 1/2\nteaspoons\nbaking powder\n1 1/2\nteaspoons\nbaking soda\n1\nteaspoon\nsalt\n2\nlarge\neggs\n, at room temperature\n1\ncup\nsour cream\n, at room temperature\n1/2\ncup\nvegetable oil\n1\ntablespoon\npure\nvanilla extract\n1/2\ncup\nboiling\nwater\n4\nounces\nbittersweet chocolate\n, finely chopped\nFor the Topping:\n2 1/2\ncups\nheavy\nor\nwhipping cream\n, chilled\n3/4\ncup\nconfectioners' sugar\n, sifted\n3\ncups\n(about\n36\nounces\n)\npitted fresh cherries\n, quartered\n2\nounces\nbittersweet chocolate\n, finely chopped\nDirections\nFor the Cake:\nBring kirsch and cherries to boil over high heat in small saucepan or in liquid measuring cup in microwave. Set aside.\nMeanwhile, adjust oven rack to middle position and preheat oven to 350\u00b0F. Lightly spray 13- by 9-inch cake pan with baking spray.\nIn large bowl, whisk together sugar, flour, cocoa, baking powder, baking soda, and salt. In medium bowl, whisk together eggs, sour cream, oil, and vanilla. Add wet ingredients to dry ingredients and stir until mixture is a thick paste.\nPour kirsch-cherry mixture into batter through a sieve, reserving cherries. Add boiling water and stir batter until smooth. Stir in reserved cherries.\nPlace chocolate in small bowl and microwave until smooth and melted, 1 to 2 minutes, stopping microwave to stir chocolate every 30 seconds. Alternatively, bring about 1 inch of water to boil in small saucepan. Place chocolate in small bowl over pan and stir until chocolate is smooth and melted, 1 to 2 minutes.\nScrape batter into prepared pan. Bake until tester inserted in center of cake comes out clean, 20 to 25 minutes. Transfer cake to cooling rack and cool completely in pan, about 1 hour.\nFor the Topping:\nWhip cream and confectioners\u2019 sugar to soft peaks by hand with large whisk or with electric mixer on medium speed and dollop over cake servings right before serving. Top with fresh cherries and chocolate.\nSpecial Equipment\nSmall saucepan or microwave, 13- by 9-inch baking pan, sieve, cooling rack, large whisk or with electric mixer\nThis Recipe Appears In\nLet Them Eat: Easy Black Forest Cake\nCakes\nGerman\nBaking\nChocolate",
  "generated_image_url": "https://ideswdhtrmrqesmfbybh.supabase.co/storage/v1/object/public/recipe-images/easy-black-forest-cake-recipe.webp?"
}