{
  "url": "https://www.seriouseats.com/homemade-kit-kat-bars-recipe",
  "image_url": "https://www.seriouseats.com/thmb/4p0PdxzsYf_NLakZ26PChq_hBKg=/1500x0/filters:no_upscale():max_bytes(150000):strip_icc()/__opt__aboutcom__coeus__resources__content_migration__serious_eats__seriouseats.com__recipes__20110119-133241-homemade-kit-kats-1-1c44a0528bb34268b9eb6724d065b367.jpg",
  "tags": [
    "Candy"
  ],
  "title": "Homemade Kit Kat Bars Recipe",
  "full_text": "Homemade Kit Kat Bars Recipe\nClose\nJump to recipe\nPrep\n15 mins\nCook\n15 mins\nActive\n45 mins\nCooling and Chilling Time\n2 hrs 30 mins\nTotal\n3 hrs\nServes\n32 bars\nCook Mode\n(Keep screen awake)\nIngredients\n75\nClub crackers\n1/2\npound\n(\n2\nsticks\n)\nunsalted butter\n2\ncups\ngraham cracker crumbs\n1\ncup\nfirmly\npacked\ndark brown sugar\n1/2\ncup\nmilk\n1/3\ncup\ngranulated sugar\n2/3\ncup\ncreamy peanut butter\n1/2\ncup\nsemisweet chocolate chips\n1/2\ncup\nbutterscotch chips\nDirections\nLine 9- by 13-inch rectangular baking pan with one layer of Club crackers (you may need to break some to fit).\nMelt butter in large saucepan over medium heat. Add graham cracker crumbs, dark brown sugar, milk, and granulated sugar. Bring to boil. Boil for five minutes, stirring constantly. Remove pan from heat. Pour half of butter mixture over crackers in pan. Smooth surface with spatula.\nArrange another layer of Club crackers over butter mixture. Pour remaining butter mixture over surface. Smooth surface with spatula. Arrange a third layer of crackers over top.\nCombine peanut butter, chocolate chips, and butterscotch chips in small saucepan. Melt over medium-low heat, stirring constantly. Spread evenly over crackers.\nCool to room temperature, then cover and refrigerate two hours. Cut into 2-inch bars. Bars will keep for two weeks, stored in an airtight container in the refrigerator.\nThis Recipe Appears In\nEdible DIY: Paula Deen's Homemade Kit Kat Bars\nCandy"
}