{
  "url": "https://www.seriouseats.com/khichdi-with-eggplant-fritters-recipe",
  "image_url": "https://www.seriouseats.com/thmb/hJHFnAAtmTl9cCG8gYlAEsF-EZE=/1500x0/filters:no_upscale():max_bytes(150000):strip_icc()/__opt__aboutcom__coeus__resources__content_migration__serious_eats__seriouseats.com__recipes__upload__2011__09__20110919-khichdi-with-eggplant-fritters-8ebd360266f64d0d8f1db74aa8e07f9a.jpg",
  "tags": [
    "Indian",
    "Frying",
    "Lentils",
    "Eggplant",
    "Potatoes"
  ],
  "title": "Beyond Curry: Khichdi with Eggplant Fritters Recipe",
  "full_text": "Beyond Curry: Khichdi with Eggplant Fritters Recipe\nClose\nJump to recipe\nPrep\n5 mins\nCook\n40 mins\nActive\n20 mins\nTotal\n45 mins\nServes\n2 servings\nCook Mode\n(Keep screen awake)\nIngredients\nFor the Khichdi:\n2\ntablespoons\nvegetable oil\n1\nmedium\nonion\n, thinly sliced (about\n1\ncup\n)\n1\n(2 inch)\nstick\ncinnamon\n3\ncloves\n1\ntablespoon\ngarlic\n, grated on a microplane grater\n1\ntablespoon\nginger\n, grated on a microplane grater\n1\ntablespoon\nground cumin\n1/2\nteaspoon\nground turmeric\n1\nmedium\npotato\n, cut into 1/2-inch dice (about\n1\ncup\n)\n6\ncauliflower\nflorettes\n(about\n1/4\ncup\n)\n1\ncup\nrice\n, washed and drained\n1\u00bd\ncups\nmixed\nlentils\n(split green gram/mung dal, split yellow gram tuvar dal, or any lentil of your choice) washed and drained\n1\nteaspoon\nred\nchilli powder\n(or more according to taste)\nKosher salt\n1/2\ncup\nchopped\ncoriander leaves\nand stems\n1\nmedium\ntomato\ncut into rounds\n4\ncups\nwater\n1/2\ntablespoon\nghee\nFor the Eggplant Fritters:\n1\nmedium\nsized\neggplant\n, about 6 inches, cut into 1/2-inch rounds\n2 1/2\ntablespoons\nsplit Bengal\ngram flour\n1\nteaspoon\nsalt\n1\nteaspoon\nground red\nchilli\n1/2\nteaspoon\nground turmeric\n2\ntablespoons\nwater\n(or a little more-to make a thick coating batter consistency)\n3\ntablespoons\nvegetable oil\nDirections\nFor the khichdi:\nHeat oil in a large saucepan over medium heat until shimmering. Add the onions and cook, stirring frequently until just beginning to brown, about 4 minutes. Add cinnamon stick and cloves and cook, stirring constantly, until fragrant, about 30 seconds. Reduce heat to low. Add garlic and ginger and cook, stirring constantly, until aromatic, about 30 seconds. Add cumin and turmeric and continue to cook over low heat, stirring constantly, until oil separates, about 1 minute longer.\nAdd the potato and cauliflower and cook, stirring constantly for 30 seconds. Add the rice and lentils and cook for one minute, stirring to coat with spices. Add the chilli powder, a pinch of salt, corriander, tomatoes, and water, and stir to combine. Bring to a boil over high heat. Cover and reduce heat to lowest possible setting and cook until rice is tender, about 10 minutes. Keep warm while making eggplant fritters.\nFor the Eggplant Fritters:\nCut the eggplant into 1-centimeter rounds. Whisk together gram flour, salt, red chilli, turmeric and water into a medium bowl. Add water and whisk to form a mixture with the consistency of pancake batter.\nHeat oil over medium high heat until shimmering. Reduce heat to low. Dip eggplant slices in batter, allow excess to drain, and cook until golden brown on both sides, 5 to 7 minutes per side. Drain, season with salt, and serve immediately with hot khichdi.\nSpecial equipment\nPressure cooker or a pot with a lid for the khichdi, frying pan and spatula for the eggplant.\nIndian\nFrying\nLentils\nEggplant\nPotatoes"
}