{
  "url": "https://www.seriouseats.com/larchmont-david-embury-cocktail-recipe",
  "image_url": "https://www.seriouseats.com/thmb/eTX9jgG0Vk2qLp4FsjibEw-KJho=/1500x0/filters:no_upscale():max_bytes(150000):strip_icc()/__opt__aboutcom__coeus__resources__content_migration__serious_eats__seriouseats.com__recipes__images__cocktailChroniclesBug-9412e94910094a1e8ea410520602d065.png",
  "tags": [
    "Rum",
    "Liqueurs & Fortified Wines"
  ],
  "title": "Larchmont Recipe",
  "full_text": "Larchmont Recipe\nClose\nJump to recipe\nPrep\n5 mins\nCook\n0 mins\nTotal\n5 mins\nServes\n1 cocktail\nCook Mode\n(Keep screen awake)\nIngredients\n1 1/2\nounces\nwhite rum\n1/2\nounce\nfresh lime juice\n1/2\nounce\nGrand Marnier\n1\nteaspoon\nsimple syrup\nDirections\nCombine ingredients in a cocktail shaker and fill with ice. Shake well for 10 seconds and strain into a chilled cocktail glass. Garnish with a twist of orange peel.\nNotes\nTo make simple syrup, combine equal parts sugar and water in a saucepan over medium heat, and whisk until sugar is completely dissolved and syrup comes just to a boil.\nRum\nLiqueurs & Fortified Wines",
  "generated_image_url": "https://ideswdhtrmrqesmfbybh.supabase.co/storage/v1/object/public/recipe-images/larchmont-recipe.webp?"
}