{
  "url": "https://www.seriouseats.com/pork-adobo-philippino-braise-recipe",
  "image_url": "https://www.seriouseats.com/thmb/YbSHblZRHkbSza0gg_15vykqDdA=/1500x0/filters:no_upscale():max_bytes(150000):strip_icc()/__opt__aboutcom__coeus__resources__content_migration__serious_eats__seriouseats.com__recipes__images__2011__12__20111229-185226-pork-adobo-315f4eeb34df42ad8798662f32f652ba.jpg",
  "tags": [
    "Pork Mains",
    "Filipino",
    "Stovetop Pork",
    "Pork Shoulder"
  ],
  "title": "Pork Adobo Recipe",
  "full_text": "Pork Adobo Recipe\nClose\nJump to recipe\nCook\n3 hrs 15 mins\nActive\n30 mins\nTotal\n3 hrs 15 mins\nServes\n4\nto 6 servings\nCook Mode\n(Keep screen awake)\nIngredients\n1\ntablespoon\noil\n3\npounds\npork shoulder\n1/2\ncup\nsoy sauce\n1/2\ncup\nrice vinegar\n, plus more to taste\n1\ncup\ncoconut milk\n4\nbay leaves\n8\ncloves\ngarlic\n, peeled and lightly crushed\nDirections\nHeat oil in a large straight-sided saut\u00e9 pan on very high heat until oil begins to smoke. Sear pork in batches, leaving plenty of open space in the pan, until a light crust forms, about 1 to 2 minutes per side.\nWhen last batch of pork is seared, return all pork to pan and add soy sauce, vinegar, coconut milk, bay leaves, and garlic. Bring to a boil, then reduce to a bare simmer and cook, covered, for 2 1/2 to 3 hours, or until pork is very tender but not completely falling apart.\nRemove pork from pan and set aside. Strain sauce into a fat separator or measuring cup and skim off fat, reserving for another use. Return sauce to pan, add about 1 tablespoon of vinegar, and cook on medium high heat until sauce reduces to less than 1 cup.\nReturn pork to thickened sauce and add salt and vinegar to taste. Serve with rice and chopped scallions for garnish.\nThis Recipe Appears In\nSpice Hunting: Bay Leaf, The Herb That Thinks It's A Spice\nPork Mains\nFilipino\nStovetop Pork\nPork Shoulder"
}