{
  "url": "https://www.seriouseats.com/sauced-spicy-beer-mustard-recipe",
  "image_url": "https://www.seriouseats.com/thmb/44k4tedHiuAMPLRZjvhG-NTMK0o=/1500x0/filters:no_upscale():max_bytes(150000):strip_icc()/__opt__aboutcom__coeus__resources__content_migration__serious_eats__seriouseats.com__recipes__images__2011__10__20111010-174505-beer-mustard-e73d922e42ed47b7afcdd57236b1e338.jpg",
  "tags": [
    "Dipping Sauce",
    "Memorial Day"
  ],
  "title": "Spicy Beer Mustard Recipe",
  "full_text": "Spicy Beer Mustard Recipe\nClose\nJump to recipe\nPrep\n5 mins\nCook\n5 mins\nActive\n15 mins\nSoaking and Cooling Time\n12 hrs 10 mins\nTotal\n12 hrs 20 mins\nServes\n24\nto 36 servings\nMakes\n3 cups\nCook Mode\n(Keep screen awake)\nIngredients\n1/3\ncup\nyellow mustard seeds\n1/4\ncup\nbrown mustard seeds\n1/2\ncup\ncider vinegar\n1\ncup\ndark beer\n, divided\n3\ntablespoons\ndark brown sugar\n2\ntablespoons\nhoney\n1\nteaspoon\nkosher salt\n1/2\nteaspoon\nturmeric\n1/8\nteaspoon\nground allspice\nDirections\nIn a small bowl, cover yellow and brown mustard seeds with vinegar and 1/2 cup of beer. Cover and place in the refrigerator overnight.\nIn a small saucepan, mix together remaining 1\u20442 cup of beer, sugar, honey, salt, turmeric, and allspice. Bring to a boil over medium heat, remove from heat, and let cool slightly.\nIn the jar of a blender add mustard seeds with their soaking liquid and cooled mixture from saucepan. Puree until smooth. Transfer to an airtight container and refrigerate overnight before using.\nSpecial equipment\nBlender\nDipping Sauce\nMemorial Day",
  "generated_image_url": "https://ideswdhtrmrqesmfbybh.supabase.co/storage/v1/object/public/recipe-images/spicy-beer-mustard-recipe.webp?"
}