{
  "url": "https://www.seriouseats.com/spiced-biscoff-sandwich-cookie-recipe",
  "image_url": "https://www.seriouseats.com/thmb/1BC2gSflTb75ISz8HVW3DoS-6-Q=/1500x0/filters:no_upscale():max_bytes(150000):strip_icc()/__opt__aboutcom__coeus__resources__content_migration__serious_eats__seriouseats.com__recipes__images__2017__05__20170414-DIY-biscoff-cookies-vicky-wasik-13-ab081fbdd18b4c6a886933699633aea4.jpg",
  "tags": [
    "Cookies"
  ],
  "title": "Spiced Biscoff Sandwich Cookies Recipe",
  "full_text": "Spiced Biscoff Sandwich Cookies Recipe\nClose\nJump to recipe\nPrep\n15 mins\nCook\n7 mins\nActive\n30 mins\nChilling and Cooling Time\n3 hrs 20 mins\nTotal\n3 hrs 42 mins\nMakes\n20 sandwiches\nCook Mode\n(Keep screen awake)\nIngredients\n1 3/4\ncups\nall-purpose flour\n3/4\nteaspoon\nbaking soda\n1 1/2\nteaspoons\ncinnamon\n1 1/2\nteaspoons\ncloves\n1 1/2\nteaspoons\nginger\n1/2\nteaspoon\nnutmeg\n1/2\nteaspoon\nsalt\n4\ntablespoons\nunsalted butter,\nat room temperature\n1/3\ncup\ndark brown sugar\n1/2\ncup\nmolasses\n2\ntablespoons\norange juice\n1\ntablespoon\norange zest\nBiscoff spread\nDirections\nIn a medium bowl, whisk together flour, baking soda, cloves, ginger, grated nutmeg, and salt.\nIn a large bowl, beat together butter and sugar until light and fluffy. Add molasses, orange juice, and zest and beat until combined. Add dry ingredients and beat until dough comes together. Divide dough in two, cover in plastic wrap, and chill for three hours in the refrigerator.\nPreheat oven to 325\u00b0F (160\u00b0C). Line a baking sheet with parchment paper.\nTake dough out of fridge and roll out on a lightly floured surface to 1/8 inch thick. (In order for cookies to be crispy, they must be as thin as possible). Cut out cookies (see note) and place on baking sheet. Bake until dry and darkened in color, about 7 minutes.\nLet cookies cool on baking sheet for 5 minutes then transfer to a wire rack. Let cool completely. Top 1/2 of cookies with about 1/2 teaspoon Biscoff spread. Top with remaining cookies to form sandwiches.\nSpecial equipment\nElectric mixer, baking sheet, 1 1/2-inch cookie cutter\nThis Recipe Appears In\nCookie Monster: Spiced Biscoff Sandwich Cookies\nCookies"
}