{
  "url": "https://www.seriouseats.com/spicy-strawberry-jalapeno-lemonade-recipe",
  "image_url": "https://www.seriouseats.com/thmb/FQNAg7cN0EY-sNOwe73dKpK5UW8=/1500x0/filters:no_upscale():max_bytes(150000):strip_icc()/__opt__aboutcom__coeus__resources__content_migration__serious_eats__seriouseats.com__recipes__images__2012__06__20120618-lemonade-variations-02-3efe3562260943858a63e5fa2f3c9a9c.jpg",
  "tags": [
    "Non-Alcoholic Drinks",
    "Lemon",
    "Strawberry",
    "Summer Drinks"
  ],
  "title": "Spicy Strawberry-Jalape\u00f1o Lemonade Recipe",
  "full_text": "Spicy Strawberry-Jalape\u00f1o Lemonade Recipe\nClose\nJump to recipe\nPrep\n5 mins\nActive\n30 mins\nMacerating Time\n30 mins\nTotal\n35 mins\nServes\n4\nto 6 servings\nCook Mode\n(Keep screen awake)\nIngredients\n1\nquart\nstrawberries\n, hulled and split in quarters lengthwise\n1/2\njalape\u00f1o\npepper\n, seeds and ribs removed, cut into\n4\npieces\n3/4\ncup\nsugar\nPinch\nsalt\n1\ncup\nfresh juice\nfrom\n10 to 12\nwhole\nlemons\n3\ncups\ncold\nwater\n1\nquart\nice\nDirections\nCombine strawberries, jalepe\u00f1o slices, sugar, and salt in a medium bowl and toss to coat. Let rest for 30 minutes.\nRemove and discard jalape\u00f1o slices. Set aside 1 cup of macerated strawberries for garnish. Transfer remaining strawberries and any exuded juices and syrup into a blender. Add lemon juice. Blend on high speed until smooth, about 1 minute. Strain through a fine mesh strainer into a pitcher. Discard solids. Add reserved strawberries and cold water and whisk to combine. Add ice. Serve in ice-filled glasses garnished with a strawberry and a jalape\u00f1o slice.\nSpecial equipment\nblender\nNon-Alcoholic Drinks\nLemon\nStrawberry\nSummer Drinks"
}